trix_editor/__init__.py
trix_editor/fields.py
trix_editor/urls.py
trix_editor/views.py
trix_editor/widgets.py
django_trix_editor-0.4.1.dist-info/LICENSE
django_trix_editor-0.4.1.dist-info/METADATA
django_trix_editor-0.4.1.dist-info/WHEEL
django_trix_editor-0.4.1.dist-info/top_level.txt
django_trix_editor-0.4.1.dist-info/RECORD
