Metadata-Version: 2.1
Name: django-trix-editor
Version: 0.4.1
Summary: Django App To Integrate Trix Editor
Home-page: https://github.com/adilkhash/django-trix-editor
Author: Adylzhan Khashtamov
Author-email: adil.khashtamov@gmail.com
License: MIT
License-File: LICENSE
Requires-Dist: Django (>=4.1)
